pyfohhn/__init__.py
pyfohhn/pyfohhn_device.py
pyfohhn/pyfohhn_fdcp.py
pyfohhn/pyfohhn_text_device.py
pyfohhn-1.2.3.dist-info/METADATA
pyfohhn-1.2.3.dist-info/WHEEL
pyfohhn-1.2.3.dist-info/licenses/LICENSE
pyfohhn-1.2.3.dist-info/RECORD
