Metadata-Version: 2.4
Name: pyfohhn
Version: 1.2.3
Summary: Python library to interact with Fohhn Speakers
License: MIT
License-File: LICENSE
Author: Stefan Strobel
Author-email: stefan.strobel@fohhn.com
Requires-Python: >=3.10,<4.0
Classifier: License :: OSI Approved :: MIT License
Classifier: Programming Language :: Python :: 3
Classifier: Programming Language :: Python :: 3.10
Classifier: Programming Language :: Python :: 3.11
Classifier: Programming Language :: Python :: 3.12
Classifier: Programming Language :: Python :: 3.13
Classifier: Programming Language :: Python :: 3.14
Requires-Dist: pyserial (>=3.5,<4.0)
Project-URL: Homepage, https://github.com/fohhn/pyfohhn
Project-URL: Repository, https://github.com/fohhn/pyfohhn
